pyseg/__init__.py
pyseg/bibtex.py
pyseg/constants.py
pyseg/icon.png
pyseg/protocols.conf
pyseg/utils.py
pyseg/wizards.py
pyseg/convert/__init__.py
pyseg/convert/convert.py
pyseg/protocols/__init__.py
pyseg/protocols/protocol_2d_classification.py
pyseg/protocols/protocol_fils.py
pyseg/protocols/protocol_graphs.py
pyseg/protocols/protocol_picking.py
pyseg/protocols/protocol_post_rec_particles.py
pyseg/protocols/protocol_pre_seg.py
pyseg/tests/__init__.py
pyseg/tests/test_posRec_classify2d.py
pyseg/tests/test_preseg_graphs_fils_picking.py
pyseg/viewers/__init__.py
pyseg/viewers/vesicle_graphs_fils_viewer.py
pyseg/viewers/vesicle_visualization_tree.py
pyseg/viewers/viewers_data.py
scipion_em_pyseg-3.1.3.dist-info/LICENSE
scipion_em_pyseg-3.1.3.dist-info/METADATA
scipion_em_pyseg-3.1.3.dist-info/WHEEL
scipion_em_pyseg-3.1.3.dist-info/entry_points.txt
scipion_em_pyseg-3.1.3.dist-info/top_level.txt
scipion_em_pyseg-3.1.3.dist-info/RECORD
