Metadata-Version: 2.1
Name: scipion-em-pyseg
Version: 3.1.3
Summary: Scipion plugin for PySeg
Home-page: https://github.com/scipion-em/scipion-em-pyseg
Author: I2PC
Author-email: scipion@cnb.csic.es
License: UNKNOWN
Keywords: scipion cryoem cryoet imageprocessing scipion-3.0
Platform: UNKNOWN
Classifier: Development Status :: 5 - Production/Stable
Classifier: License :: OSI Approved :: GNU General Public License v3 (GPLv3)
Classifier: Programming Language :: Python :: 3
Requires-Dist: scipion-em-tomo
Requires-Dist: scipion-em-tomoviz
Requires-Dist: scipion-em-reliontomo
